dbcooper/__init__.py
dbcooper/base.py
dbcooper/collect.py
dbcooper/dbcooper.py
dbcooper/finder.py
dbcooper/inspect.py
dbcooper/tables.py
dbcooper/utils.py
dbcooper/data/__init__.py
dbcooper/data/lahman.py
dbcooper/tests/conftest.py
dbcooper/tests/helpers.py
dbcooper/tests/test_example_schemas.py
dbcooper-0.0.8.dist-info/licenses/LICENSE
dbcooper-0.0.8.dist-info/METADATA
dbcooper-0.0.8.dist-info/WHEEL
dbcooper-0.0.8.dist-info/top_level.txt
dbcooper-0.0.8.dist-info/RECORD
