Metadata-Version: 2.4
Name: dbcooper
Version: 0.0.8
Summary: The dbcooper package turns a database connection into a collection of functions, handling logic for keeping track of connections and letting you take advantage of autocompletion when exploring a database.
Author-email: Michael Chow <mc_al_github@fastmail.com>
License: MIT
Keywords: template,packaging
Classifier: Programming Language :: Python :: 3.8
Classifier: Programming Language :: Python :: 3.9
Classifier: Programming Language :: Python :: 3.10
Requires-Python: >=3.10
License-File: LICENSE
Requires-Dist: sqlalchemy
Requires-Dist: tabulate
Provides-Extra: siuba
Requires-Dist: siuba>=0.4.4; extra == "siuba"
Dynamic: license-file
